pyclarify/__init__.py
pyclarify/client.py
pyclarify/experimental.py
pyclarify/__utils__/__init__.py
pyclarify/__utils__/auxiliary.py
pyclarify/__utils__/exceptions.py
pyclarify/__utils__/pagination.py
pyclarify/__utils__/payload.py
pyclarify/__utils__/stopping_conditions.py
pyclarify/__utils__/time.py
pyclarify/__utils__/warnings.py
pyclarify/fields/__init__.py
pyclarify/fields/authentication.py
pyclarify/fields/constraints.py
pyclarify/fields/dataframe.py
pyclarify/fields/error.py
pyclarify/fields/query.py
pyclarify/fields/resource.py
pyclarify/jsonrpc/__init__.py
pyclarify/jsonrpc/client.py
pyclarify/jsonrpc/oauth2.py
pyclarify/query/__init__.py
pyclarify/query/filter.py
pyclarify/query/query.py
pyclarify/views/__init__.py
pyclarify/views/dataframe.py
pyclarify/views/evaluate.py
pyclarify/views/generics.py
pyclarify/views/items.py
pyclarify/views/signals.py
pyclarify-0.6.8.dist-info/licenses/LICENSE
pyclarify-0.6.8.dist-info/licenses/LICENSE.txt
pyclarify-0.6.8.dist-info/METADATA
pyclarify-0.6.8.dist-info/WHEEL
pyclarify-0.6.8.dist-info/top_level.txt
pyclarify-0.6.8.dist-info/RECORD
