Metadata-Version: 2.4
Name: pyclarify
Version: 0.6.8
Summary: Python SDK for reading and writing signals to Clarify.
Home-page: https://github.com/clarify/pyclarify
Author: Odd Gunnar Aspaas
Author-email: odd.gunnar@clarify.io
License: MIT
Project-URL: Bug Tracker, https://github.com/clarify/pyclarify/issues
Classifier: Programming Language :: Python :: 3
Classifier: License :: OSI Approved :: MIT License
Classifier: Operating System :: OS Independent
Requires-Python: >=3.10
License-File: LICENSE
License-File: LICENSE.txt
Requires-Dist: requests
Requires-Dist: pydantic~=2.0
Provides-Extra: dev
Requires-Dist: pytest; extra == "dev"
Requires-Dist: black; extra == "dev"
Requires-Dist: mypy; extra == "dev"
Dynamic: license-file
